[{"dunsnumber":"801423062","vendorname":"CARDINAL HEALTH, INC.","smb":"O: OTHER THAN SMALL BUSINESS","pred":"3356.626220703125"},
{"dunsnumber":"80241867","vendorname":"FORD MOTOR COMPANY","smb":"O: OTHER THAN SMALL BUSINESS","pred":"2383.645751953125"},
{"dunsnumber":"6906614","vendorname":"BERGEN BRUNSWIG DRUG COMPANY","smb":"O: OTHER THAN SMALL BUSINESS","pred":"2167.665283203125"},
{"dunsnumber":"7914906","vendorname":"AMERISOURCEBERGEN DRUG CORPORATION","smb":"O: OTHER THAN SMALL BUSINESS","pred":"1358.8746337890625"},
{"dunsnumber":"7941230","vendorname":"OWENS & MINOR DISTRIBUTION, INC.","smb":"O: OTHER THAN SMALL BUSINESS","pred":"871.1589965820312"},
{"dunsnumber":"961027315","vendorname":"CARDINAL HEALTH 200 INCORPORATED THE MEDICAL PRODUCTS AND SERVICES GROUP OF CAR","smb":"S: SMALL BUSINESS","pred":"744.7620849609375"},
{"dunsnumber":"148983229","vendorname":"SCIENCE APPLICATIONS INTERNATIONAL CORPORATION","smb":"O: OTHER THAN SMALL BUSINESS","pred":"609.6344604492188"},
{"dunsnumber":"105919864","vendorname":"MCKESSON CORPORATION","smb":"O: OTHER THAN SMALL BUSINESS","pred":"603.6860961914062"},
{"dunsnumber":"76916246","vendorname":"INVACARE CORPORATION","smb":"S: SMALL BUSINESS","pred":"600.01416015625"},
{"dunsnumber":"147795132","vendorname":"ALLAN BAKER, INC.","smb":"O: OTHER THAN SMALL BUSINESS","pred":"588.24462890625"},
{"dunsnumber":"155415078","vendorname":"ALPHA OFFICE SUPPLIES, INC","smb":"S: SMALL BUSINESS","pred":"510.8750915527344"},
{"dunsnumber":"831587949","vendorname":"CHRYSLER GROUP, LLC, THE","smb":"O: OTHER THAN SMALL BUSINESS","pred":"468.2355041503906"},
{"dunsnumber":"5083209","vendorname":"BAXTER HEALTHCARE CORPORATION","smb":"O: OTHER THAN SMALL BUSINESS","pred":"429.9276428222656"},
{"dunsnumber":"884194044","vendorname":"S J GAJDOS INCORPORATED","smb":"S: SMALL BUSINESS","pred":"401.1692810058594"},
{"dunsnumber":"10018737","vendorname":"AARCO PRODUCTS INC","smb":"O: OTHER THAN SMALL BUSINESS","pred":"390.2961120605469"},
{"dunsnumber":"25460908","vendorname":"MEDLINE INDUSTRIES INCORPORATED","smb":"O: OTHER THAN SMALL BUSINESS","pred":"362.9286193847656"},
{"dunsnumber":"962972159","vendorname":"LOCKHEED MARTIN CORPORATION","smb":"O: OTHER THAN SMALL BUSINESS","pred":"356.3064270019531"},
{"dunsnumber":"804514602","vendorname":"CONFIGURATION INCORPORATED","smb":"S: SMALL BUSINESS","pred":"346.6982421875"},
{"dunsnumber":"791451180","vendorname":"CARDINAL HEALTH 100, INC","smb":"S: SMALL BUSINESS","pred":"345.99176025390625"},
{"dunsnumber":"142440150","vendorname":"JORDAN RESES SUPPLY COMPANY, LLC","smb":"O: OTHER THAN SMALL BUSINESS","pred":"334.8316650390625"},
{"dunsnumber":"137361572","vendorname":"MCKESSON HBOC, INC","smb":"O: OTHER THAN SMALL BUSINESS","pred":"331.7962951660156"},
{"dunsnumber":"883533879","vendorname":"DMS PHARMACEUTICAL GROUP INC.","smb":"O: OTHER THAN SMALL BUSINESS","pred":"310.98114013671875"},
{"dunsnumber":"77817617","vendorname":"HP ENTERPRISE SERVICES, LLC","smb":"O: OTHER THAN SMALL BUSINESS","pred":"301.800537109375"},
{"dunsnumber":"1123314","vendorname":"LAMSON AND GOODNOW MANUFACTURING COMPANY","smb":"S: SMALL BUSINESS","pred":"298.0260925292969"},
{"dunsnumber":"67943220","vendorname":"LOCKHEED MARTIN AERONAUTICS SERVICE-INTERNATIONAL","smb":"O: OTHER THAN SMALL BUSINESS","pred":"297.10516357421875"},
{"dunsnumber":"1667161","vendorname":"MICHELIN NORTH AMERICA, INC.","smb":"O: OTHER THAN SMALL BUSINESS","pred":"287.1924743652344"},
{"dunsnumber":"79308359","vendorname":"SEALED AIR CORPORATION","smb":"S: SMALL BUSINESS","pred":"286.14544677734375"},
{"dunsnumber":"21717889","vendorname":"BOSTON SCIENTIFIC CORPORATION","smb":"S: SMALL BUSINESS","pred":"270.5152282714844"},
{"dunsnumber":"169601999","vendorname":"COOK MEDICAL INC","smb":"O: OTHER THAN SMALL BUSINESS","pred":"264.031005859375"},
{"dunsnumber":"785347691","vendorname":"TRC GLOBAL SOLUTIONS, INC.","smb":"S: SMALL BUSINESS","pred":"263.05877685546875"},
{"dunsnumber":"9255191","vendorname":"J.L. DARLING CORPORATION","smb":"S: SMALL BUSINESS","pred":"253.01943969726562"},
{"dunsnumber":"966410859","vendorname":"NEXEO SOLUTIONS, LLC","smb":"O: OTHER THAN SMALL BUSINESS","pred":"247.66815185546875"},
{"dunsnumber":"54537840","vendorname":"APEX FOOT HEALTH INDUSTRIES INCORPORATED","smb":"S: SMALL BUSINESS","pred":"228.60693359375"},
{"dunsnumber":"5527098","vendorname":"HOLLISTER INCORPORATED","smb":"O: OTHER THAN SMALL BUSINESS","pred":"226.001220703125"},
{"dunsnumber":"828128475","vendorname":"WILLOW ENVIRONMENTAL, INC.","smb":"S: SMALL BUSINESS","pred":"214.4084930419922"},
{"dunsnumber":"622051969","vendorname":"CNA CORPORATION","smb":"O: OTHER THAN SMALL BUSINESS","pred":"204.54637145996094"},
{"dunsnumber":"44081388","vendorname":"PROCURENET, INC","smb":"O: OTHER THAN SMALL BUSINESS","pred":"202.2235107421875"},
{"dunsnumber":"74809377","vendorname":"NISH","smb":"O: OTHER THAN SMALL BUSINESS","pred":"188.07347106933594"},
{"dunsnumber":"793477758","vendorname":"TINKER SUPPORT SERVICES JV","smb":"O: OTHER THAN SMALL BUSINESS","pred":"179.85739135742188"},
{"dunsnumber":"147286269","vendorname":"LOCKHEED MARTIN CORPORATION","smb":"O: OTHER THAN SMALL BUSINESS","pred":"176.50686645507812"},
{"dunsnumber":"158704010","vendorname":"QUANTELL, INC.","smb":"S: SMALL BUSINESS","pred":"176.28599548339844"},
{"dunsnumber":"76339782","vendorname":"I-SOLUTIONS DIRECT, INC.","smb":"O: OTHER THAN SMALL BUSINESS","pred":"176.11026000976562"},
{"dunsnumber":"147329176","vendorname":"LOCKHEED MARTIN CORPORATION","smb":"O: OTHER THAN SMALL BUSINESS","pred":"174.1988525390625"},
{"dunsnumber":"831765891","vendorname":"BIMBO FOODS, INC.","smb":"O: OTHER THAN SMALL BUSINESS","pred":"173.0841522216797"},
{"dunsnumber":"71595540","vendorname":"CONMED CORPORATION","smb":"O: OTHER THAN SMALL BUSINESS","pred":"170.41561889648438"},
{"dunsnumber":"835551474","vendorname":"SIKORSKY AIRCRAFT CORPORATION","smb":"O: OTHER THAN SMALL BUSINESS","pred":"169.54811096191406"},
{"dunsnumber":"6217061","vendorname":"DAKOTA DRUG INC","smb":"S: SMALL BUSINESS","pred":"163.11874389648438"},
{"dunsnumber":"90706516","vendorname":"WHR GROUP, INC","smb":"O: OTHER THAN SMALL BUSINESS","pred":"163.03726196289062"},
{"dunsnumber":"75957076","vendorname":"BINDLEY WESTERN INDUSTRIES INC","smb":"O: OTHER THAN SMALL BUSINESS","pred":"161.78318786621094"},
{"dunsnumber":"785809349","vendorname":"GENERAL DYNAMICS INFORMATION TECHNOLOGY, INC.","smb":"O: OTHER THAN SMALL BUSINESS","pred":"161.7221221923828"},
{"dunsnumber":"808576024","vendorname":"ALLIED JOINT VENTURE","smb":"S: SMALL BUSINESS","pred":"158.02911376953125"},
{"dunsnumber":"49365591","vendorname":"DG21 LIMITED LIABILITY COMPANY","smb":"O: OTHER THAN SMALL BUSINESS","pred":"157.79498291015625"},
{"dunsnumber":"781457148","vendorname":"TRI STATE GOVERNMENT SERVICES","smb":"S: SMALL BUSINESS","pred":"157.43536376953125"},
{"dunsnumber":"967162251","vendorname":"REDSTONE DEFENSE SYSTEMS","smb":"S: SMALL BUSINESS","pred":"152.19747924804688"},
{"dunsnumber":"88162420","vendorname":"U.S. FOODSERVICE, INC.","smb":"O: OTHER THAN SMALL BUSINESS","pred":"151.3970947265625"},
{"dunsnumber":"16290632","vendorname":"AMERICAN BUSINESS FORMS","smb":"S: SMALL BUSINESS","pred":"144.37237548828125"},
{"dunsnumber":"152791091","vendorname":"NORTHROP GRUMMAN SPACE & MISSI","smb":"O: OTHER THAN SMALL BUSINESS","pred":"143.98471069335938"},
{"dunsnumber":"962900288","vendorname":"BENTCO OFFICE SOLUTIONS","smb":"S: SMALL BUSINESS","pred":"143.4481201171875"},
{"dunsnumber":"8018525","vendorname":"ALCON LABORATORIES, INC.","smb":"S: SMALL BUSINESS","pred":"140.57763671875"},
{"dunsnumber":"41477449","vendorname":"PRIDE MOBILITY PRODUCTS CORPORATION","smb":"S: SMALL BUSINESS","pred":"140.24717712402344"},
{"dunsnumber":"623191194","vendorname":"DENTAL HEALTH PRODUCTS INCORPORATED","smb":"S: SMALL BUSINESS","pred":"133.04977416992188"},
{"dunsnumber":"827861662","vendorname":"JOHNSON CONTROLS BUILDING AUTOMATION SYSTEMS LLC","smb":"O: OTHER THAN SMALL BUSINESS","pred":"131.3360137939453"},
{"dunsnumber":"780456294","vendorname":"L 3 COMMUNICATIONS FLIGHT INTERNATIONAL AVIATION LIMITED LIABILITY COMPANY","smb":"O: OTHER THAN SMALL BUSINESS","pred":"131.14035034179688"},
{"dunsnumber":"154773337","vendorname":"SAFETY EQUIPMENT COMPANY","smb":"O: OTHER THAN SMALL BUSINESS","pred":"130.71177673339844"},
{"dunsnumber":"159868624","vendorname":"SYSCO FOOD SERVICES OF RALEIGH, LLC","smb":"O: OTHER THAN SMALL BUSINESS","pred":"129.28408813476562"},
{"dunsnumber":"859395428","vendorname":"DEPUY ORTHOPAEDICS, INC.","smb":"S: SMALL BUSINESS","pred":"129.18728637695312"},
{"dunsnumber":"31576887","vendorname":"HOLLAND OPTICAL INCORPORATED","smb":"S: SMALL BUSINESS","pred":"126.71310424804688"},
{"dunsnumber":"39309179","vendorname":"NORTH AMERICAN AIRLINES","smb":"O: OTHER THAN SMALL BUSINESS","pred":"125.39591217041016"},
{"dunsnumber":"782053516","vendorname":"JOHNSON & JOHNSON HEALTH CARE SYSTEMS INC.","smb":"O: OTHER THAN SMALL BUSINESS","pred":"123.71781158447266"},
{"dunsnumber":"21411467","vendorname":"KLARQUIST SPARKMAN, LLP","smb":"O: OTHER THAN SMALL BUSINESS","pred":"123.4643783569336"},
{"dunsnumber":"155104938","vendorname":"COASTAL PACIFIC FOOD DISTRIBUT","smb":"S: SMALL BUSINESS","pred":"122.02177429199219"},
{"dunsnumber":"12430880","vendorname":"HENRY SCHEIN INCORPORATED","smb":"O: OTHER THAN SMALL BUSINESS","pred":"120.35990905761719"},
{"dunsnumber":"7258460","vendorname":"BARNETT & RAMEL OPTICAL CO OF NEBRASKA","smb":"S: SMALL BUSINESS","pred":"120.19290924072266"},
{"dunsnumber":"62722038","vendorname":"AMERICAN PURCHASING SERVICES, INC.","smb":"O: OTHER THAN SMALL BUSINESS","pred":"117.52751159667969"},
{"dunsnumber":"13550462","vendorname":"PEERLESS AEROSPACE FASTENER CORPORATION","smb":"O: OTHER THAN SMALL BUSINESS","pred":"116.45281219482422"},
{"dunsnumber":"4323481","vendorname":"HOMER LAUGHLIN CHINA CO, THE","smb":"O: OTHER THAN SMALL BUSINESS","pred":"114.78314971923828"},
{"dunsnumber":"80911274","vendorname":"BAE SYSTEMS SAN DIEGO SHIP REPAIR INC.","smb":"O: OTHER THAN SMALL BUSINESS","pred":"114.21493530273438"},
{"dunsnumber":"115369472","vendorname":"LS&S LIMITED LIABILITY COMPANY","smb":"S: SMALL BUSINESS","pred":"113.6221923828125"},
{"dunsnumber":"6261481","vendorname":"MEDTRONIC, INC.","smb":"S: SMALL BUSINESS","pred":"112.70620727539062"},
{"dunsnumber":"93115632","vendorname":"BALLARD MEDICAL PRODUCTS","smb":"O: OTHER THAN SMALL BUSINESS","pred":"111.8760986328125"},
{"dunsnumber":"142877732","vendorname":"EVERGREEN INTERNATIONAL AIRLINES INCORPORATED","smb":"O: OTHER THAN SMALL BUSINESS","pred":"109.8218002319336"},
{"dunsnumber":"878053321","vendorname":"LAND-O-SUN DAIRIES L.L.C.","smb":"O: OTHER THAN SMALL BUSINESS","pred":"109.0887222290039"},
{"dunsnumber":"182043083","vendorname":"TIMBER EDGE MACHINE","smb":"S: SMALL BUSINESS","pred":"108.11986541748047"},
{"dunsnumber":"120808360","vendorname":"OTO TECH LIMITED LIABILITY COMPANY","smb":"S: SMALL BUSINESS","pred":"107.28429412841797"},
{"dunsnumber":"153718502","vendorname":"FEDEX CORPORATION","smb":"O: OTHER THAN SMALL BUSINESS","pred":"106.68555450439453"},
{"dunsnumber":"85737968","vendorname":"AUTOMATED SCIENCES GROUP, INC","smb":"O: OTHER THAN SMALL BUSINESS","pred":"105.04965209960938"},
{"dunsnumber":"361267339","vendorname":"TETRA TECH EM INCORPORATED","smb":"O: OTHER THAN SMALL BUSINESS","pred":"102.6902847290039"},
{"dunsnumber":"835568965","vendorname":"SYSCO FOOD SERVICES OF SEATTLE","smb":"O: OTHER THAN SMALL BUSINESS","pred":"100.62554931640625"},
{"dunsnumber":"825054810","vendorname":"EMERALD SERVICES, INC.","smb":"S: SMALL BUSINESS","pred":"100.02181243896484"},
{"dunsnumber":"177360039","vendorname":"STERIS CORPORATION","smb":"S: SMALL BUSINESS","pred":"99.47901916503906"},
{"dunsnumber":"96372255","vendorname":"DEROYAL INDUSTRIES INCORPORATED","smb":"O: OTHER THAN SMALL BUSINESS","pred":"98.89778900146484"},
{"dunsnumber":"10712461","vendorname":"TRI ANIM HEALTH SERVICES INCORPORATED","smb":"S: SMALL BUSINESS","pred":"98.4460678100586"},
{"dunsnumber":"155505485","vendorname":"RAYTHEON TECHNICAL SERVICES COMPANY LLC","smb":"O: OTHER THAN SMALL BUSINESS","pred":"98.36760711669922"},
{"dunsnumber":"614163707","vendorname":"AA WHEEL & TRUCK SUPPLY, INC.","smb":"S: SMALL BUSINESS","pred":"97.78736877441406"},
{"dunsnumber":"72831415","vendorname":"ARROW INTERNATIONAL INCORPORATED","smb":"S: SMALL BUSINESS","pred":"96.96053314208984"},
{"dunsnumber":"49765910","vendorname":"SAFE-LITE OPTICAL CO., INC.","smb":"S: SMALL BUSINESS","pred":"96.6936264038086"},
{"dunsnumber":"627785884","vendorname":"ARROWHEAD GLOBAL SOLUTIONS, IN","smb":"O: OTHER THAN SMALL BUSINESS","pred":"96.19483184814453"},
{"dunsnumber":"43683515","vendorname":"TRENDWAY CORPORATION","smb":"S: SMALL BUSINESS","pred":"95.93412017822266"},
{"dunsnumber":"1292192","vendorname":"BECTON DICKINSON AND COMPANY","smb":"O: OTHER THAN SMALL BUSINESS","pred":"95.8083724975586"},
{"dunsnumber":"604483321","vendorname":"BREG INCORPORATED","smb":"O: OTHER THAN SMALL BUSINESS","pred":"95.04473876953125"}]