[{"vendorname":"NATIONAL INDUSTRIES FOR THE BL","dunsnumber":"1672120","pred":"157190.83","smb":"O: OTHER THAN SMALL BUSINESS"},
{"vendorname":"BOISE CASCADE OFFICE PRODUCTS","dunsnumber":"879436640","pred":"39483.45169274999","smb":"O: OTHER THAN SMALL BUSINESS"},
{"vendorname":"OFFICE DEPOT","dunsnumber":"614345809","pred":"21953.32033983333","smb":"S: SMALL BUSINESS"},
{"vendorname":"MBA OFFICE SUPPLY INCORPORATED","dunsnumber":"24042079","pred":"7253.1714","smb":"O: OTHER THAN SMALL BUSINESS"},
{"vendorname":"VETERANS IMAGING PRODUCTS, INC","dunsnumber":"938054723","pred":"5548.1115703333335","smb":"S: SMALL BUSINESS"},
{"vendorname":"SUPPLIES NOW, INC.","dunsnumber":"147768563","pred":"5526.3774","smb":"S: SMALL BUSINESS"},
{"vendorname":"VALLEY INDUSTRIAL PRODUCTS, INC.","dunsnumber":"2640084","pred":"5306.2095","smb":"S: SMALL BUSINESS"},
{"vendorname":"WECSYS LIMITED LIABILITY COMPANY (6769)","dunsnumber":"836284091","pred":"5150.3574","smb":"O: OTHER THAN SMALL BUSINESS"},
{"vendorname":"ELLISON SYSTEMS INCORPORATED","dunsnumber":"942173550","pred":"4788.0005","smb":"O: OTHER THAN SMALL BUSINESS"},
{"vendorname":"GEORGE W  ALLEN CO , INC","dunsnumber":"24212375","pred":"4227.148","smb":"S: SMALL BUSINESS"},
{"vendorname":"NISH INC","dunsnumber":"74809377","pred":"3623.4468","smb":"O: OTHER THAN SMALL BUSINESS"},
{"vendorname":"MMG TECHNOLOGY GROUP INC","dunsnumber":"81722436","pred":"3372.8032","smb":"S: SMALL BUSINESS"},
{"vendorname":"UNICOR / FEDERAL PRISON INDUSTRIES (3594)","dunsnumber":"626627459","pred":"2942.252","smb":"O: OTHER THAN SMALL BUSINESS"},
{"vendorname":"SUMMIT TRAVELWARE INC","dunsnumber":"193567856","pred":"2695.37981635","smb":"S: SMALL BUSINESS"},
{"vendorname":"CORPORATE EXPRESS OFFICE PRODUCTS INCORPORATED","dunsnumber":"933457251","pred":"1881.8291","smb":"O: OTHER THAN SMALL BUSINESS"},
{"vendorname":"STAPLES BUSINESS EXPO A DIVISION OF STAPLES INCORPORATED","dunsnumber":"942603358","pred":"1490.4991645555554","smb":"O: OTHER THAN SMALL BUSINESS"},
{"vendorname":"ASSOCIATED INDUSTRIES FOR THE BLIND","dunsnumber":"47157701","pred":"1466.4924","smb":"S: SMALL BUSINESS"},
{"vendorname":"NORTHEAST OFFICE SUPPLY CO  LL","dunsnumber":"131876737","pred":"1387.5112","smb":"S: SMALL BUSINESS"},
{"vendorname":"OFFICE DEPOT, INC","dunsnumber":"153531108","pred":"1311.9758","smb":"O: OTHER THAN SMALL BUSINESS"},
{"vendorname":"SUPPLY SAVER CORPORATION (INC)","dunsnumber":"130484660","pred":"1263.6141","smb":"S: SMALL BUSINESS"},
{"vendorname":"SKM INDUSTRIES INC","dunsnumber":"809108459","pred":"1236.1134","smb":"S: SMALL BUSINESS"},
{"vendorname":"MISCELLANEOUS FOREIGN AWARDEES","dunsnumber":"123456787","pred":"946.7998416769228","smb":"O: OTHER THAN SMALL BUSINESS"},
{"vendorname":"TRANSPARENT OFFICE PRODUCTS LIMITED LIABILITY COMPANY","dunsnumber":"48042386","pred":"868.1446","smb":"S: SMALL BUSINESS"},
{"vendorname":"ABM FEDERAL SALES INC","dunsnumber":"64632888","pred":"798.1525543272727","smb":"O: OTHER THAN SMALL BUSINESS"},
{"vendorname":"ALLIANCE RUBBER COMPANY","dunsnumber":"6561450","pred":"752.905","smb":"S: SMALL BUSINESS"},
{"vendorname":"APPLIED DATA RESOURCES INCORPORATED","dunsnumber":"175002799","pred":"752.09454","smb":"O: OTHER THAN SMALL BUSINESS"},
{"vendorname":"INTERIOR FACILITIES DESIGN LLC","dunsnumber":"184200785","pred":"737.68555","smb":"S: SMALL BUSINESS"},
{"vendorname":"KIPPER TOOL COMPANY","dunsnumber":"828953166","pred":"704.82916","smb":"S: SMALL BUSINESS"},
{"vendorname":"PREMIER AND COMPANIES INCORPORATED","dunsnumber":"784141384","pred":"680.2981646042857","smb":"S: SMALL BUSINESS"},
{"vendorname":"UNITED OFFICE SOLUTIONS INCORPORATED","dunsnumber":"137469768","pred":"678.8481048","smb":"O: OTHER THAN SMALL BUSINESS"},
{"vendorname":"METRO OFFICE SOLUTIONS, INC.","dunsnumber":"787411917","pred":"647.3982854666667","smb":"O: OTHER THAN SMALL BUSINESS"},
{"vendorname":"NEW YORK INKJET LIMITED LIABILITY COMPANY","dunsnumber":"610959467","pred":"643.6073","smb":"S: SMALL BUSINESS"},
{"vendorname":"S&B COMPUTER AND OFFICE PRODUCTS INCORPORATED","dunsnumber":"803875343","pred":"628.56085","smb":"S: SMALL BUSINESS"},
{"vendorname":"B & D SUPPLIES, INC.","dunsnumber":"52460821","pred":"612.43","smb":"S: SMALL BUSINESS"},
{"vendorname":"RIBBONS EXPRESS, INC","dunsnumber":"783587751","pred":"594.0681","smb":"S: SMALL BUSINESS"},
{"vendorname":"CAPP INCORPORATED","dunsnumber":"14654966","pred":"594.03235","smb":"O: OTHER THAN SMALL BUSINESS"},
{"vendorname":"ANTEON CORPORATION","dunsnumber":"67641597","pred":"592.2349","smb":"O: OTHER THAN SMALL BUSINESS"},
{"vendorname":"LUCILLE MAUD CORPORATION","dunsnumber":"193976974","pred":"591.5706","smb":"S: SMALL BUSINESS"},
{"vendorname":"DELPHIN COMPUTER SUPPLY","dunsnumber":"156967036","pred":"566.92423775","smb":"S: SMALL BUSINESS"},
{"vendorname":"A S E DIRECT LIMITED LIABILITY COMPANY","dunsnumber":"616385667","pred":"544.7560184666667","smb":"O: OTHER THAN SMALL BUSINESS"},
{"vendorname":"PROGRESSIVE LASER INC","dunsnumber":"958768343","pred":"538.3357874249999","smb":"S: SMALL BUSINESS"},
{"vendorname":"MILLENNIUM SOLUTIONS INC","dunsnumber":"48673698","pred":"533.0717","smb":"S: SMALL BUSINESS"},
{"vendorname":"AMERICAN BUSINESS FORMS","dunsnumber":"16290632","pred":"529.1614","smb":"S: SMALL BUSINESS"},
{"vendorname":"CAPITOL FURNITURE DISTRIBUTING COMPANY","dunsnumber":"131781643","pred":"525.1457","smb":"O: OTHER THAN SMALL BUSINESS"},
{"vendorname":"ENVISION XPRESS, INC.","dunsnumber":"118860779","pred":"524.1461","smb":"O: OTHER THAN SMALL BUSINESS"},
{"vendorname":"ARKANSAS LIGHTHOUSE FOR THE BLIND, THE","dunsnumber":"75638171","pred":"522.452","smb":"O: OTHER THAN SMALL BUSINESS"},
{"vendorname":"RECYCLED OFFICE PRODUCTS COMPANY","dunsnumber":"809475692","pred":"505.89374","smb":"S: SMALL BUSINESS"},
{"vendorname":"CADDO DESIGN INC","dunsnumber":"781083662","pred":"505.10782","smb":"S: SMALL BUSINESS"},
{"vendorname":"BUHRMANN US INC","dunsnumber":"164871878","pred":"501.10413","smb":"S: SMALL BUSINESS"},
{"vendorname":"WESCO AIRCRAFT HARDWARE CORP.","dunsnumber":"48485478","pred":"477.64243","smb":"S: SMALL BUSINESS"},
{"vendorname":"ECONOFFICE PRODUCTS & SUPPLIES, INC.","dunsnumber":"158147459","pred":"422.52887","smb":"S: SMALL BUSINESS"},
{"vendorname":"RELIANT BUSINESS PRODUCTS INCORPORATED","dunsnumber":"8106684","pred":"410.86554","smb":"S: SMALL BUSINESS"},
{"vendorname":"ALEXANDER SUPPLY CO., INC.","dunsnumber":"5908413","pred":"398.06375","smb":"S: SMALL BUSINESS"},
{"vendorname":"INDEPENDENT STATIONERS, INC","dunsnumber":"85625200","pred":"393.24314159999994","smb":"S: SMALL BUSINESS"},
{"vendorname":"IMPAC COMPUTER SUPPLIES INC.","dunsnumber":"44332844","pred":"390.5387","smb":"S: SMALL BUSINESS"},
{"vendorname":"UNITED PARCEL SERVICE INCORPORATED (OH) (2075)","dunsnumber":"128729373","pred":"388.57617","smb":"O: OTHER THAN SMALL BUSINESS"},
{"vendorname":"PELICAN PRODUCTS INCORPORATED","dunsnumber":"82193277","pred":"364.03696","smb":"O: OTHER THAN SMALL BUSINESS"},
{"vendorname":"SPECIALTY LOOSELEAF INCORPORATED","dunsnumber":"867167587","pred":"350.0215799999999","smb":"S: SMALL BUSINESS"},
{"vendorname":"CAPRICE ELECTRONICS, INC.","dunsnumber":"92658152","pred":"349.25104","smb":"O: OTHER THAN SMALL BUSINESS"},
{"vendorname":"ACCESS PRODUCTS INC","dunsnumber":"151045309","pred":"343.9546","smb":"O: OTHER THAN SMALL BUSINESS"},
{"vendorname":"ADVANCED DIGITAL SOLUTIONS INTERNATIONAL","dunsnumber":"793965609","pred":"337.58292","smb":"S: SMALL BUSINESS"},
{"vendorname":"INDUSTRIES FOR THE BLIND, INC","dunsnumber":"6096200","pred":"330.958266275","smb":"O: OTHER THAN SMALL BUSINESS"},
{"vendorname":"CAROLINA MARKING DEVICES INC","dunsnumber":"3150190","pred":"326.74774","smb":"S: SMALL BUSINESS"},
{"vendorname":"PACIFIC INK, INC.","dunsnumber":"115419470","pred":"325.69614","smb":"S: SMALL BUSINESS"},
{"vendorname":"CELLCO PARTNERSHIP DBA VERIZON WIRELESS","dunsnumber":"968904698","pred":"318.27316","smb":"S: SMALL BUSINESS"},
{"vendorname":"S & W MANUFACTURING","dunsnumber":"613491653","pred":"314.0553300000001","smb":"O: OTHER THAN SMALL BUSINESS"},
{"vendorname":"DIVINE IMAGING INCORPORATED","dunsnumber":"132080123","pred":"313.25075999999996","smb":"O: OTHER THAN SMALL BUSINESS"},
{"vendorname":"S & T OFFICE PRODUCTS INC","dunsnumber":"57102238","pred":"312.70105","smb":"S: SMALL BUSINESS"},
{"vendorname":"ATLANTIC DIVING SUPPLY, INC.","dunsnumber":"27079776","pred":"310.84285785","smb":"O: OTHER THAN SMALL BUSINESS"},
{"vendorname":"TIMEMED LABELING SYSTEMS, INC","dunsnumber":"3853488","pred":"299.824","smb":"O: OTHER THAN SMALL BUSINESS"},
{"vendorname":"BOISE CASCADE OFFICE PRODUCTS","dunsnumber":"620497891","pred":"296.69452","smb":"O: OTHER THAN SMALL BUSINESS"},
{"vendorname":"COMPLETE PACKAGING AND SHIPPING SUPPLIES INCORPORATED","dunsnumber":"790889711","pred":"292.57572999750005","smb":"S: SMALL BUSINESS"},
{"vendorname":"K PAUL PROPERTIES, LLC","dunsnumber":"785308797","pred":"286.44888","smb":"S: SMALL BUSINESS"},
{"vendorname":"WEBER COMPUTER SUPPLY COMPANY","dunsnumber":"613480586","pred":"273.92117","smb":"O: OTHER THAN SMALL BUSINESS"},
{"vendorname":"VETERAN CORPS OF AMERICA","dunsnumber":"187409060","pred":"272.67923","smb":"S: SMALL BUSINESS"},
{"vendorname":"THE ARBOR SCHOOL","dunsnumber":"556359966","pred":"270.81534","smb":"O: OTHER THAN SMALL BUSINESS"},
{"vendorname":"AMERICAN OFFICE PRODUCTS DISTR","dunsnumber":"39636337","pred":"265.0007486566667","smb":"S: SMALL BUSINESS"},
{"vendorname":"ALL CITI TONER INC.","dunsnumber":"16792058","pred":"264.49457","smb":"S: SMALL BUSINESS"},
{"vendorname":"BERGAMO GROUP BUSINESS SOLUTIONS INCORPORATED","dunsnumber":"131096211","pred":"263.6869","smb":"S: SMALL BUSINESS"},
{"vendorname":"WATS INTERNATIONAL INC","dunsnumber":"101284552","pred":"260.3897","smb":"S: SMALL BUSINESS"},
{"vendorname":"B2B DIRECT","dunsnumber":"13497342","pred":"259.57153","smb":"S: SMALL BUSINESS"},
{"vendorname":"EZ PRINT SUPPLIES","dunsnumber":"141254842","pred":"259.35886","smb":"S: SMALL BUSINESS"},
{"vendorname":"SZY HOLDINGS, LLC","dunsnumber":"147372960","pred":"254.72868","smb":"S: SMALL BUSINESS"},
{"vendorname":"COMPUTER SCIENCES CORPORATION","dunsnumber":"43991108","pred":"253.47942","smb":"O: OTHER THAN SMALL BUSINESS"},
{"vendorname":"WRIGHT TOOL COMPANY","dunsnumber":"57007189","pred":"253.41708","smb":"S: SMALL BUSINESS"},
{"vendorname":"OFFICE PRODUCTS","dunsnumber":"147043103","pred":"252.53682","smb":"S: SMALL BUSINESS"},
{"vendorname":"ST LOUIS CRAYON AND SOAPSTONE INCORPORATED","dunsnumber":"7857766","pred":"250.2964","smb":"S: SMALL BUSINESS"},
{"vendorname":"METRO OFFICE PRODUCTS LLC","dunsnumber":"791326312","pred":"249.86915101249997","smb":"S: SMALL BUSINESS"},
{"vendorname":"ACORN OFFICE PRODUCTS LLC","dunsnumber":"192770050","pred":"247.94608","smb":"O: OTHER THAN SMALL BUSINESS"},
{"vendorname":"T & M COMPUTER SUPPLY CO","dunsnumber":"95260410","pred":"247.93575","smb":"S: SMALL BUSINESS"},
{"vendorname":"XSE GROUP, INC.","dunsnumber":"161854054","pred":"247.81079","smb":"S: SMALL BUSINESS"},
{"vendorname":"SERCO INC.","dunsnumber":"928859149","pred":"242.52295","smb":"O: OTHER THAN SMALL BUSINESS"},
{"vendorname":"FRANKLIN COVEY CO","dunsnumber":"113402713","pred":"242.45016","smb":"S: SMALL BUSINESS"},
{"vendorname":"SUN SUPPLY INCORPORATED","dunsnumber":"131067675","pred":"239.96136","smb":"S: SMALL BUSINESS"},
{"vendorname":"APRISA TECHNOLOGY,LLC","dunsnumber":"129983776","pred":"238.93695","smb":"S: SMALL BUSINESS"},
{"vendorname":"LYNN ELECTRONICS CORP.","dunsnumber":"2387603","pred":"237.07826","smb":"S: SMALL BUSINESS"},
{"vendorname":"OFFICE GROUP, INC., THE","dunsnumber":"119079903","pred":"236.40851749500004","smb":"O: OTHER THAN SMALL BUSINESS"},
{"vendorname":"OFFICE ESSENTIALS COMPANY","dunsnumber":"151263022","pred":"234.18839","smb":"S: SMALL BUSINESS"},
{"vendorname":"GENERAL ELECTRIC COMPANY","dunsnumber":"73838534","pred":"229.80011","smb":"S: SMALL BUSINESS"},
{"vendorname":"FORD MOTOR COMPANY","dunsnumber":"80241867","pred":"229.1982","smb":"O: OTHER THAN SMALL BUSINESS"}]